bertdotwebadapter/__init__.py
bertdotwebadapter/logger.py
bertdotwebadapter-0.0.6.dist-info/METADATA
bertdotwebadapter-0.0.6.dist-info/WHEEL
bertdotwebadapter-0.0.6.dist-info/top_level.txt
bertdotwebadapter-0.0.6.dist-info/RECORD
